liltab/__init__.py
liltab/data/dataloaders.py
liltab/data/datasets.py
liltab/data/factory.py
liltab/data/preprocessing.py
liltab/model/heterogenous_attributes_network.py
liltab/model/utils.py
liltab/train/logger.py
liltab/train/trainer.py
liltab/train/utils.py
liltab-1.0.6.dist-info/LICENSE
liltab-1.0.6.dist-info/METADATA
liltab-1.0.6.dist-info/WHEEL
liltab-1.0.6.dist-info/top_level.txt
liltab-1.0.6.dist-info/RECORD
