Metadata-Version: 2.1
Name: liltab
Version: 1.0.6
Summary: Package for meta-learning across data with varying attributes spaces.
Author-email: "Antoni Zajko, Dawid Płudowski" <antoni.zajko.1@gmail.com>
Project-URL: Homepage, https://github.com/azoz01/liltab
Classifier: Programming Language :: Python :: 3
Classifier: License :: OSI Approved :: MIT License
Classifier: Operating System :: OS Independent
Requires-Python: >=3.8
License-File: LICENSE
Requires-Dist: torch >=2.0
Requires-Dist: pandas >=2.0
Requires-Dist: numpy >=1.25.0
Requires-Dist: scikit-learn >=1.3.0
Requires-Dist: pytorch-lightning >=2.0.6
Requires-Dist: tensorboard >=2.14.0
